rfpkit_cli/__init__.py
rfpkit_cli/templates/checklist-template.md
rfpkit_cli/templates/guidelines-template.md
rfpkit_cli/templates/section-template.md
rfpkit_cli/templates/strategy-template.md
rfpkit_cli/templates/tasks-template.md
rfpkit_cli/templates/vscode-settings.json
rfpkit_cli/templates/commands/analyze.md
rfpkit_cli/templates/commands/checklist.md
rfpkit_cli/templates/commands/clarify.md
rfpkit_cli/templates/commands/competitive.md
rfpkit_cli/templates/commands/compliance.md
rfpkit_cli/templates/commands/draft.md
rfpkit_cli/templates/commands/guidelines.md
rfpkit_cli/templates/commands/pricing.md
rfpkit_cli/templates/commands/section.md
rfpkit_cli/templates/commands/strategy.md
rfpkit_cli/templates/commands/tasks.md
rfpkit_cli/templates/commands/taskstoissues.md
rfpkit_cli/templates/prompts/rfpkit.analyze.prompt.md
rfpkit_cli/templates/prompts/rfpkit.checklist.prompt.md
rfpkit_cli/templates/prompts/rfpkit.clarify.prompt.md
rfpkit_cli/templates/prompts/rfpkit.competitive.prompt.md
rfpkit_cli/templates/prompts/rfpkit.compliance.prompt.md
rfpkit_cli/templates/prompts/rfpkit.draft.prompt.md
rfpkit_cli/templates/prompts/rfpkit.guidelines.prompt.md
rfpkit_cli/templates/prompts/rfpkit.pricing.prompt.md
rfpkit_cli/templates/prompts/rfpkit.section.prompt.md
rfpkit_cli/templates/prompts/rfpkit.strategy.prompt.md
rfpkit_cli/templates/prompts/rfpkit.tasks.prompt.md
rfpkit_cli/templates/prompts/rfpkit.taskstoissues.prompt.md
rfpkit_cli-0.1.3.dist-info/METADATA
rfpkit_cli-0.1.3.dist-info/WHEEL
rfpkit_cli-0.1.3.dist-info/entry_points.txt
rfpkit_cli-0.1.3.dist-info/licenses/LICENSE
rfpkit_cli-0.1.3.dist-info/RECORD
