Metadata-Version: 2.4
Name: rfpkit-cli
Version: 0.1.3
Summary: RFP Kit - A framework for structured RFP response development using AI agents.
Project-URL: Homepage, https://github.com/sketabchi/rfpkit
Project-URL: Documentation, https://github.com/sketabchi/rfpkit#readme
Project-URL: Repository, https://github.com/sketabchi/rfpkit
Project-URL: Bug Reports, https://github.com/sketabchi/rfpkit/issues
Project-URL: Changelog, https://github.com/sketabchi/rfpkit/blob/main/CHANGELOG.md
Author-email: Shahrokh Ektabchi <sketabchi@users.noreply.github.com>
Maintainer-email: Shahrokh Ektabchi <sketabchi@users.noreply.github.com>
License: MIT License
License-File: LICENSE
Keywords: ai,automation,business,cli,proposal,rfp
Classifier: Development Status :: 4 - Beta
Classifier: Environment :: Console
Classifier: Intended Audience :: Developers
Classifier: Intended Audience :: End Users/Desktop
Classifier: License :: OSI Approved :: MIT License
Classifier: Operating System :: OS Independent
Classifier: Programming Language :: Python :: 3
Classifier: Programming Language :: Python :: 3.11
Classifier: Programming Language :: Python :: 3.12
Classifier: Programming Language :: Python :: 3.13
Classifier: Topic :: Office/Business
Classifier: Topic :: Software Development :: Libraries :: Application Frameworks
Classifier: Topic :: Text Processing :: Markup
Classifier: Typing :: Typed
Requires-Python: >=3.11
Requires-Dist: httpx[socks]
Requires-Dist: platformdirs
Requires-Dist: readchar
Requires-Dist: rich
Requires-Dist: truststore>=0.10.4
Requires-Dist: typer
